{"commitInfo":{"timestamp":1731185887251,"operation":"WRITE","operationParameters":{"mode":"Append","partitionBy":"[]"},"isolationLevel":"Serializable","isBlindAppend":true,"operationMetrics":{"numFiles":"12","numOutputRows":"1000","numOutputBytes":"40997"},"engineInfo":"Apache-Spark/3.5.3 Delta-Lake/3.2.1","txnId":"afcf14fd-25cf-406a-a585-c1d37de3d5ab"}}
{"metaData":{"id":"ccc2b8ab-1f6b-4b22-85df-95f80b34db7a","format":{"provider":"parquet","options":{}},"schemaString":"{\"type\":\"struct\",\"fields\":[{\"name\":\"emotion\",\"type\":\"string\",\"nullable\":true,\"metadata\":{}},{\"name\":\"typingSpeed\",\"type\":\"integer\",\"nullable\":true,\"metadata\":{}},{\"name\":\"syntaxErrors\",\"type\":\"integer\",\"nullable\":true,\"metadata\":{}},{\"name\":\"windowSwitchCount\",\"type\":\"integer\",\"nullable\":true,\"metadata\":{}},{\"name\":\"received_at\",\"type\":\"string\",\"nullable\":true,\"metadata\":{}},{\"name\":\"timestamp\",\"type\":\"string\",\"nullable\":true,\"metadata\":{}}]}","partitionColumns":[],"configuration":{},"createdTime":1731185885253}}
{"protocol":{"minReaderVersion":1,"minWriterVersion":2}}
{"add":{"path":"part-00000-81521670-a7f0-42b7-b941-a0af1b1d476c-c000.snappy.parquet","partitionValues":{},"size":3394,"modificationTime":1731185887153,"dataChange":true,"stats":"{\"numRecords\":83,\"minValues\":{\"emotion\":\"angry\",\"typingSpeed\":22,\"syntaxErrors\":0,\"windowSwitchCount\":0,\"received_at\":\"2024-11-09T15:58:03.863204\",\"timestamp\":\"2024-11-09T15:58:03.863213\"},\"maxValues\":{\"emotion\":\"sad\",\"typingSpeed\":80,\"syntaxErrors\":5,\"windowSwitchCount\":10,\"received_at\":\"2024-11-09T15:58:03.863493\",\"timestamp\":\"2024-11-09T15:58:03.863493\"},\"nullCount\":{\"emotion\":0,\"typingSpeed\":0,\"syntaxErrors\":0,\"windowSwitchCount\":0,\"received_at\":0,\"timestamp\":0}}"}}
{"add":{"path":"part-00001-5ba4ff57-99e9-4bc3-86f7-65332dc8fbc0-c000.snappy.parquet","partitionValues":{},"size":3402,"modificationTime":1731185887153,"dataChange":true,"stats":"{\"numRecords\":83,\"minValues\":{\"emotion\":\"angry\",\"typingSpeed\":21,\"syntaxErrors\":0,\"windowSwitchCount\":0,\"received_at\":\"2024-11-09T15:58:03.863496\",\"timestamp\":\"2024-11-09T15:58:03.863497\"},\"maxValues\":{\"emotion\":\"sad\",\"typingSpeed\":80,\"syntaxErrors\":5,\"windowSwitchCount\":10,\"received_at\":\"2024-11-09T15:58:03.863849\",\"timestamp\":\"2024-11-09T15:58:03.863850\"},\"nullCount\":{\"emotion\":0,\"typingSpeed\":0,\"syntaxErrors\":0,\"windowSwitchCount\":0,\"received_at\":0,\"timestamp\":0}}"}}
{"add":{"path":"part-00002-2a717d65-b3a1-4d6c-b621-70eb3502b982-c000.snappy.parquet","partitionValues":{},"size":3435,"modificationTime":1731185887153,"dataChange":true,"stats":"{\"numRecords\":83,\"minValues\":{\"emotion\":\"angry\",\"typingSpeed\":21,\"syntaxErrors\":0,\"windowSwitchCount\":0,\"received_at\":\"2024-11-09T15:58:03.863852\",\"timestamp\":\"2024-11-09T15:58:03.863853\"},\"maxValues\":{\"emotion\":\"sad\",\"typingSpeed\":80,\"syntaxErrors\":5,\"windowSwitchCount\":10,\"received_at\":\"2024-11-09T15:58:03.864118\",\"timestamp\":\"2024-11-09T15:58:03.864119\"},\"nullCount\":{\"emotion\":0,\"typingSpeed\":0,\"syntaxErrors\":0,\"windowSwitchCount\":0,\"received_at\":0,\"timestamp\":0}}"}}
{"add":{"path":"part-00003-5b1b9211-ba06-4c16-8834-d26f217dfe2c-c000.snappy.parquet","partitionValues":{},"size":3391,"modificationTime":1731185887153,"dataChange":true,"stats":"{\"numRecords\":83,\"minValues\":{\"emotion\":\"angry\",\"typingSpeed\":20,\"syntaxErrors\":0,\"windowSwitchCount\":0,\"received_at\":\"2024-11-09T15:58:03.864121\",\"timestamp\":\"2024-11-09T15:58:03.864122\"},\"maxValues\":{\"emotion\":\"sad\",\"typingSpeed\":79,\"syntaxErrors\":5,\"windowSwitchCount\":10,\"received_at\":\"2024-11-09T15:58:03.864387\",\"timestamp\":\"2024-11-09T15:58:03.864388\"},\"nullCount\":{\"emotion\":0,\"typingSpeed\":0,\"syntaxErrors\":0,\"windowSwitchCount\":0,\"received_at\":0,\"timestamp\":0}}"}}
{"add":{"path":"part-00004-2bcadba0-0694-44bd-8dac-d706ea37d482-c000.snappy.parquet","partitionValues":{},"size":3412,"modificationTime":1731185887153,"dataChange":true,"stats":"{\"numRecords\":83,\"minValues\":{\"emotion\":\"angry\",\"typingSpeed\":20,\"syntaxErrors\":0,\"windowSwitchCount\":0,\"received_at\":\"2024-11-09T15:58:03.864390\",\"timestamp\":\"2024-11-09T15:58:03.864391\"},\"maxValues\":{\"emotion\":\"sad\",\"typingSpeed\":80,\"syntaxErrors\":5,\"windowSwitchCount\":10,\"received_at\":\"2024-11-09T15:58:03.864655\",\"timestamp\":\"2024-11-09T15:58:03.864655\"},\"nullCount\":{\"emotion\":0,\"typingSpeed\":0,\"syntaxErrors\":0,\"windowSwitchCount\":0,\"received_at\":0,\"timestamp\":0}}"}}
{"add":{"path":"part-00005-bcb6cacc-9519-4e05-8282-d088afe1c3de-c000.snappy.parquet","partitionValues":{},"size":3421,"modificationTime":1731185887153,"dataChange":true,"stats":"{\"numRecords\":83,\"minValues\":{\"emotion\":\"angry\",\"typingSpeed\":20,\"syntaxErrors\":0,\"windowSwitchCount\":0,\"received_at\":\"2024-11-09T15:58:03.864658\",\"timestamp\":\"2024-11-09T15:58:03.864659\"},\"maxValues\":{\"emotion\":\"sad\",\"typingSpeed\":78,\"syntaxErrors\":5,\"windowSwitchCount\":10,\"received_at\":\"2024-11-09T15:58:03.864928\",\"timestamp\":\"2024-11-09T15:58:03.864929\"},\"nullCount\":{\"emotion\":0,\"typingSpeed\":0,\"syntaxErrors\":0,\"windowSwitchCount\":0,\"received_at\":0,\"timestamp\":0}}"}}
{"add":{"path":"part-00006-eec9715a-b9ee-4687-b6bd-95b27997179d-c000.snappy.parquet","partitionValues":{},"size":3426,"modificationTime":1731185887153,"dataChange":true,"stats":"{\"numRecords\":83,\"minValues\":{\"emotion\":\"angry\",\"typingSpeed\":20,\"syntaxErrors\":0,\"windowSwitchCount\":0,\"received_at\":\"2024-11-09T15:58:03.864931\",\"timestamp\":\"2024-11-09T15:58:03.864932\"},\"maxValues\":{\"emotion\":\"sad\",\"typingSpeed\":80,\"syntaxErrors\":5,\"windowSwitchCount\":10,\"received_at\":\"2024-11-09T15:58:03.865207\",\"timestamp\":\"2024-11-09T15:58:03.865208\"},\"nullCount\":{\"emotion\":0,\"typingSpeed\":0,\"syntaxErrors\":0,\"windowSwitchCount\":0,\"received_at\":0,\"timestamp\":0}}"}}
{"add":{"path":"part-00007-3cc84b5e-8641-4ab8-af2a-2ce639aa474d-c000.snappy.parquet","partitionValues":{},"size":3410,"modificationTime":1731185887153,"dataChange":true,"stats":"{\"numRecords\":83,\"minValues\":{\"emotion\":\"angry\",\"typingSpeed\":21,\"syntaxErrors\":0,\"windowSwitchCount\":0,\"received_at\":\"2024-11-09T15:58:03.865210\",\"timestamp\":\"2024-11-09T15:58:03.865211\"},\"maxValues\":{\"emotion\":\"sad\",\"typingSpeed\":79,\"syntaxErrors\":5,\"windowSwitchCount\":10,\"received_at\":\"2024-11-09T15:58:03.865471\",\"timestamp\":\"2024-11-09T15:58:03.865472\"},\"nullCount\":{\"emotion\":0,\"typingSpeed\":0,\"syntaxErrors\":0,\"windowSwitchCount\":0,\"received_at\":0,\"timestamp\":0}}"}}
{"add":{"path":"part-00008-fd3c2b9a-58e1-4076-96d8-20359572caf3-c000.snappy.parquet","partitionValues":{},"size":3415,"modificationTime":1731185887153,"dataChange":true,"stats":"{\"numRecords\":83,\"minValues\":{\"emotion\":\"angry\",\"typingSpeed\":20,\"syntaxErrors\":0,\"windowSwitchCount\":0,\"received_at\":\"2024-11-09T15:58:03.865474\",\"timestamp\":\"2024-11-09T15:58:03.865475\"},\"maxValues\":{\"emotion\":\"sad\",\"typingSpeed\":79,\"syntaxErrors\":5,\"windowSwitchCount\":10,\"received_at\":\"2024-11-09T15:58:03.865736\",\"timestamp\":\"2024-11-09T15:58:03.865736\"},\"nullCount\":{\"emotion\":0,\"typingSpeed\":0,\"syntaxErrors\":0,\"windowSwitchCount\":0,\"received_at\":0,\"timestamp\":0}}"}}
{"add":{"path":"part-00009-893c51f2-76a2-456f-82c8-7d6926e1d09f-c000.snappy.parquet","partitionValues":{},"size":3405,"modificationTime":1731185887153,"dataChange":true,"stats":"{\"numRecords\":83,\"minValues\":{\"emotion\":\"angry\",\"typingSpeed\":20,\"syntaxErrors\":0,\"windowSwitchCount\":0,\"received_at\":\"2024-11-09T15:58:03.865739\",\"timestamp\":\"2024-11-09T15:58:03.865739\"},\"maxValues\":{\"emotion\":\"sad\",\"typingSpeed\":80,\"syntaxErrors\":5,\"windowSwitchCount\":10,\"received_at\":\"2024-11-09T15:58:03.866000\",\"timestamp\":\"2024-11-09T15:58:03.866000\"},\"nullCount\":{\"emotion\":0,\"typingSpeed\":0,\"syntaxErrors\":0,\"windowSwitchCount\":0,\"received_at\":0,\"timestamp\":0}}"}}
{"add":{"path":"part-00010-fb87e29e-e0b2-498d-870c-e16be7b1579c-c000.snappy.parquet","partitionValues":{},"size":3412,"modificationTime":1731185887153,"dataChange":true,"stats":"{\"numRecords\":83,\"minValues\":{\"emotion\":\"angry\",\"typingSpeed\":20,\"syntaxErrors\":0,\"windowSwitchCount\":0,\"received_at\":\"2024-11-09T15:58:03.866003\",\"timestamp\":\"2024-11-09T15:58:03.866004\"},\"maxValues\":{\"emotion\":\"sad\",\"typingSpeed\":78,\"syntaxErrors\":5,\"windowSwitchCount\":10,\"received_at\":\"2024-11-09T15:58:03.866287\",\"timestamp\":\"2024-11-09T15:58:03.866288\"},\"nullCount\":{\"emotion\":0,\"typingSpeed\":0,\"syntaxErrors\":0,\"windowSwitchCount\":0,\"received_at\":0,\"timestamp\":0}}"}}
{"add":{"path":"part-00011-d5692e5e-9d9c-4f07-b547-85109d2be2d4-c000.snappy.parquet","partitionValues":{},"size":3474,"modificationTime":1731185887153,"dataChange":true,"stats":"{\"numRecords\":87,\"minValues\":{\"emotion\":\"angry\",\"typingSpeed\":20,\"syntaxErrors\":0,\"windowSwitchCount\":0,\"received_at\":\"2024-11-09T15:58:03.866291\",\"timestamp\":\"2024-11-09T15:58:03.866291\"},\"maxValues\":{\"emotion\":\"sad\",\"typingSpeed\":80,\"syntaxErrors\":5,\"windowSwitchCount\":10,\"received_at\":\"2024-11-09T15:58:03.866565\",\"timestamp\":\"2024-11-09T15:58:03.866566\"},\"nullCount\":{\"emotion\":0,\"typingSpeed\":0,\"syntaxErrors\":0,\"windowSwitchCount\":0,\"received_at\":0,\"timestamp\":0}}"}}
