{"commitInfo":{"timestamp":1731179371257,"operation":"WRITE","operationParameters":{"mode":"Append","partitionBy":"[\"emotion\"]"},"readVersion":3,"isolationLevel":"Serializable","isBlindAppend":true,"operationMetrics":{"numFiles":"1","numOutputRows":"1","numOutputBytes":"1804"},"engineInfo":"Apache-Spark/3.4.4 Delta-Lake/2.4.0","txnId":"a8c54405-48fc-4f6d-b01e-f4c5ea908d44"}}
{"add":{"path":"emotion=neutral/part-00011-fa5e8bd9-f7ea-4757-b6eb-2fdb11751ddf.c000.snappy.parquet","partitionValues":{"emotion":"neutral"},"size":1804,"modificationTime":1731179371254,"dataChange":true,"stats":"{\"numRecords\":1,\"minValues\":{\"typingSpeed\":0,\"syntaxErrors\":0,\"windowSwitchCount\":0,\"received_at\":\"2024-11-09T14:09:31.111658\",\"timestamp\":\"2024-11-09T14:09:31.111683\"},\"maxValues\":{\"typingSpeed\":0,\"syntaxErrors\":0,\"windowSwitchCount\":0,\"received_at\":\"2024-11-09T14:09:31.111658\",\"timestamp\":\"2024-11-09T14:09:31.111683\"},\"nullCount\":{\"typingSpeed\":0,\"syntaxErrors\":0,\"windowSwitchCount\":0,\"received_at\":0,\"timestamp\":0}}"}}
