{"commitInfo":{"timestamp":1731179702911,"operation":"WRITE","operationParameters":{"mode":"Append","partitionBy":"[\"emotion\"]"},"readVersion":67,"isolationLevel":"Serializable","isBlindAppend":true,"operationMetrics":{"numFiles":"1","numOutputRows":"1","numOutputBytes":"1804"},"engineInfo":"Apache-Spark/3.4.4 Delta-Lake/2.4.0","txnId":"1e0a1643-4bba-4671-9641-de6bb2f11e50"}}
{"add":{"path":"emotion=happy/part-00011-25380d48-a015-47da-a750-db0131e0282f.c000.snappy.parquet","partitionValues":{"emotion":"happy"},"size":1804,"modificationTime":1731179702908,"dataChange":true,"stats":"{\"numRecords\":1,\"minValues\":{\"typingSpeed\":0,\"syntaxErrors\":0,\"windowSwitchCount\":0,\"received_at\":\"2024-11-09T14:15:02.730425\",\"timestamp\":\"2024-11-09T14:15:02.730457\"},\"maxValues\":{\"typingSpeed\":0,\"syntaxErrors\":0,\"windowSwitchCount\":0,\"received_at\":\"2024-11-09T14:15:02.730425\",\"timestamp\":\"2024-11-09T14:15:02.730457\"},\"nullCount\":{\"typingSpeed\":0,\"syntaxErrors\":0,\"windowSwitchCount\":0,\"received_at\":0,\"timestamp\":0}}"}}
